package okhttp3.internal.e;

import d.a;
import d.e;
import d.r;
import d.s;
import d.t;
import java.io.EOFException;
import java.io.IOException;
import java.io.InterruptedIOException;
import java.net.SocketTimeoutException;
import java.util.List;

public final class i
{
  long bytesLeftInWriteWindow;
  final g daV;
  final b dbv;
  final a dbw;
  final c dbx = new c();
  final c dby = new c();
  b dbz = null;
  boolean hasResponseHeaders;
  final int id;
  private final List<c> requestHeaders;
  List<c> responseHeaders;
  long unacknowledgedBytesRead = 0L;
  
  static
  {
    if (!i.class.desiredAssertionStatus()) {}
    for (boolean bool = true;; bool = false)
    {
      $assertionsDisabled = bool;
      return;
    }
  }
  
  i(int paramInt, g paramg, boolean paramBoolean1, boolean paramBoolean2, List<c> paramList)
  {
    if (paramg == null) {
      throw new NullPointerException("connection == null");
    }
    if (paramList == null) {
      throw new NullPointerException("requestHeaders == null");
    }
    this.id = paramInt;
    this.daV = paramg;
    this.bytesLeftInWriteWindow = paramg.dbe.getInitialWindowSize();
    this.dbv = new b(paramg.dbd.getInitialWindowSize());
    this.dbw = new a();
    this.dbv.finished = paramBoolean2;
    this.dbw.finished = paramBoolean1;
    this.requestHeaders = paramList;
  }
  
  private boolean d(b paramb)
  {
    assert (!Thread.holdsLock(this));
    try
    {
      if (this.dbz != null) {
        return false;
      }
      if ((this.dbv.finished) && (this.dbw.finished)) {
        return false;
      }
    }
    finally {}
    this.dbz = paramb;
    notifyAll();
    this.daV.fT(this.id);
    return true;
  }
  
  public final r MX()
  {
    try
    {
      if ((!this.hasResponseHeaders) && (!isLocallyInitiated())) {
        throw new IllegalStateException("reply before requesting the sink");
      }
    }
    finally {}
    return this.dbw;
  }
  
  final void addBytesToWriteWindow(long paramLong)
  {
    this.bytesLeftInWriteWindow += paramLong;
    if (paramLong > 0L) {
      notifyAll();
    }
  }
  
  public final void b(b paramb)
    throws IOException
  {
    if (!d(paramb)) {
      return;
    }
    this.daV.b(this.id, paramb);
  }
  
  public final void c(b paramb)
  {
    if (!d(paramb)) {
      return;
    }
    this.daV.a(this.id, paramb);
  }
  
  final void cancelStreamIfNecessary()
    throws IOException
  {
    assert (!Thread.holdsLock(this));
    for (;;)
    {
      try
      {
        boolean bool;
        if ((!this.dbv.finished) && (this.dbv.closed))
        {
          if (this.dbw.finished) {
            break label112;
          }
          if (this.dbw.closed)
          {
            break label112;
            bool = isOpen();
            if (i == 0) {
              break label95;
            }
            b(b.dat);
            return;
          }
        }
        i = 0;
        continue;
        if (bool) {
          continue;
        }
      }
      finally {}
      label95:
      this.daV.fT(this.id);
      return;
      label112:
      int i = 1;
    }
  }
  
  final void checkOutNotClosed()
    throws IOException
  {
    if (this.dbw.closed) {
      throw new IOException("stream closed");
    }
    if (this.dbw.finished) {
      throw new IOException("stream finished");
    }
    if (this.dbz != null) {
      throw new n(this.dbz);
    }
  }
  
  final void e(b paramb)
  {
    try
    {
      if (this.dbz == null)
      {
        this.dbz = paramb;
        notifyAll();
      }
      return;
    }
    finally
    {
      paramb = finally;
      throw paramb;
    }
  }
  
  public final boolean isLocallyInitiated()
  {
    if ((this.id & 0x1) == 1) {}
    for (int i = 1; this.daV.client == i; i = 0) {
      return true;
    }
    return false;
  }
  
  /* Error */
  public final boolean isOpen()
  {
    // Byte code:
    //   0: iconst_0
    //   1: istore_1
    //   2: aload_0
    //   3: monitorenter
    //   4: aload_0
    //   5: getfield 62	okhttp3/internal/e/i:dbz	Lokhttp3/internal/e/b;
    //   8: astore_3
    //   9: aload_3
    //   10: ifnull +7 -> 17
    //   13: aload_0
    //   14: monitorexit
    //   15: iload_1
    //   16: ireturn
    //   17: aload_0
    //   18: getfield 97	okhttp3/internal/e/i:dbv	Lokhttp3/internal/e/i$b;
    //   21: getfield 103	okhttp3/internal/e/i$b:finished	Z
    //   24: ifne +13 -> 37
    //   27: aload_0
    //   28: getfield 97	okhttp3/internal/e/i:dbv	Lokhttp3/internal/e/i$b;
    //   31: getfield 155	okhttp3/internal/e/i$b:closed	Z
    //   34: ifeq +32 -> 66
    //   37: aload_0
    //   38: getfield 100	okhttp3/internal/e/i:dbw	Lokhttp3/internal/e/i$a;
    //   41: getfield 104	okhttp3/internal/e/i$a:finished	Z
    //   44: ifne +13 -> 57
    //   47: aload_0
    //   48: getfield 100	okhttp3/internal/e/i:dbw	Lokhttp3/internal/e/i$a;
    //   51: getfield 156	okhttp3/internal/e/i$a:closed	Z
    //   54: ifeq +12 -> 66
    //   57: aload_0
    //   58: getfield 130	okhttp3/internal/e/i:hasResponseHeaders	Z
    //   61: istore_2
    //   62: iload_2
    //   63: ifne -50 -> 13
    //   66: iconst_1
    //   67: istore_1
    //   68: goto -55 -> 13
    //   71: astore_3
    //   72: aload_0
    //   73: monitorexit
    //   74: aload_3
    //   75: athrow
    // Local variable table:
    //   start	length	slot	name	signature
    //   0	76	0	this	i
    //   1	67	1	bool1	boolean
    //   61	2	2	bool2	boolean
    //   8	2	3	localb	b
    //   71	4	3	localObject	Object
    // Exception table:
    //   from	to	target	type
    //   4	9	71	finally
    //   17	37	71	finally
    //   37	57	71	finally
    //   57	62	71	finally
  }
  
  final void receiveFin()
  {
    assert (!Thread.holdsLock(this));
    try
    {
      this.dbv.finished = true;
      boolean bool = isOpen();
      notifyAll();
      if (!bool) {
        this.daV.fT(this.id);
      }
      return;
    }
    finally {}
  }
  
  /* Error */
  public final List<c> takeResponseHeaders()
    throws IOException
  {
    // Byte code:
    //   0: aload_0
    //   1: monitorenter
    //   2: aload_0
    //   3: invokevirtual 133	okhttp3/internal/e/i:isLocallyInitiated	()Z
    //   6: ifne +18 -> 24
    //   9: new 135	java/lang/IllegalStateException
    //   12: dup
    //   13: ldc -71
    //   15: invokespecial 138	java/lang/IllegalStateException:<init>	(Ljava/lang/String;)V
    //   18: athrow
    //   19: astore_1
    //   20: aload_0
    //   21: monitorexit
    //   22: aload_1
    //   23: athrow
    //   24: aload_0
    //   25: getfield 58	okhttp3/internal/e/i:dbx	Lokhttp3/internal/e/i$c;
    //   28: invokevirtual 188	okhttp3/internal/e/i$c:enter	()V
    //   31: aload_0
    //   32: getfield 190	okhttp3/internal/e/i:responseHeaders	Ljava/util/List;
    //   35: ifnonnull +27 -> 62
    //   38: aload_0
    //   39: getfield 62	okhttp3/internal/e/i:dbz	Lokhttp3/internal/e/b;
    //   42: ifnonnull +20 -> 62
    //   45: aload_0
    //   46: invokevirtual 193	okhttp3/internal/e/i:waitForIo	()V
    //   49: goto -18 -> 31
    //   52: astore_1
    //   53: aload_0
    //   54: getfield 58	okhttp3/internal/e/i:dbx	Lokhttp3/internal/e/i$c;
    //   57: invokevirtual 196	okhttp3/internal/e/i$c:exitAndThrowIfTimedOut	()V
    //   60: aload_1
    //   61: athrow
    //   62: aload_0
    //   63: getfield 58	okhttp3/internal/e/i:dbx	Lokhttp3/internal/e/i$c;
    //   66: invokevirtual 196	okhttp3/internal/e/i$c:exitAndThrowIfTimedOut	()V
    //   69: aload_0
    //   70: getfield 190	okhttp3/internal/e/i:responseHeaders	Ljava/util/List;
    //   73: astore_1
    //   74: aload_1
    //   75: ifnull +12 -> 87
    //   78: aload_0
    //   79: aconst_null
    //   80: putfield 190	okhttp3/internal/e/i:responseHeaders	Ljava/util/List;
    //   83: aload_0
    //   84: monitorexit
    //   85: aload_1
    //   86: areturn
    //   87: new 174	okhttp3/internal/e/n
    //   90: dup
    //   91: aload_0
    //   92: getfield 62	okhttp3/internal/e/i:dbz	Lokhttp3/internal/e/b;
    //   95: invokespecial 176	okhttp3/internal/e/n:<init>	(Lokhttp3/internal/e/b;)V
    //   98: athrow
    // Local variable table:
    //   start	length	slot	name	signature
    //   0	99	0	this	i
    //   19	4	1	localObject1	Object
    //   52	9	1	localObject2	Object
    //   73	13	1	localList	List
    // Exception table:
    //   from	to	target	type
    //   2	19	19	finally
    //   24	31	19	finally
    //   53	62	19	finally
    //   62	74	19	finally
    //   78	83	19	finally
    //   87	99	19	finally
    //   31	49	52	finally
  }
  
  final void waitForIo()
    throws InterruptedIOException
  {
    try
    {
      wait();
      return;
    }
    catch (InterruptedException localInterruptedException)
    {
      throw new InterruptedIOException();
    }
  }
  
  final class a
    implements r
  {
    boolean closed;
    private final d.c dbA = new d.c();
    boolean finished;
    
    static
    {
      if (!i.class.desiredAssertionStatus()) {}
      for (boolean bool = true;; bool = false)
      {
        $assertionsDisabled = bool;
        return;
      }
    }
    
    a() {}
    
    /* Error */
    private void emitFrame(boolean paramBoolean)
      throws IOException
    {
      // Byte code:
      //   0: aload_0
      //   1: getfield 32	okhttp3/internal/e/i$a:dbB	Lokhttp3/internal/e/i;
      //   4: astore 5
      //   6: aload 5
      //   8: monitorenter
      //   9: aload_0
      //   10: getfield 32	okhttp3/internal/e/i$a:dbB	Lokhttp3/internal/e/i;
      //   13: getfield 47	okhttp3/internal/e/i:dby	Lokhttp3/internal/e/i$c;
      //   16: invokevirtual 52	okhttp3/internal/e/i$c:enter	()V
      //   19: aload_0
      //   20: getfield 32	okhttp3/internal/e/i$a:dbB	Lokhttp3/internal/e/i;
      //   23: getfield 56	okhttp3/internal/e/i:bytesLeftInWriteWindow	J
      //   26: lconst_0
      //   27: lcmp
      //   28: ifgt +60 -> 88
      //   31: aload_0
      //   32: getfield 58	okhttp3/internal/e/i$a:finished	Z
      //   35: ifne +53 -> 88
      //   38: aload_0
      //   39: getfield 60	okhttp3/internal/e/i$a:closed	Z
      //   42: ifne +46 -> 88
      //   45: aload_0
      //   46: getfield 32	okhttp3/internal/e/i$a:dbB	Lokhttp3/internal/e/i;
      //   49: getfield 64	okhttp3/internal/e/i:dbz	Lokhttp3/internal/e/b;
      //   52: ifnonnull +36 -> 88
      //   55: aload_0
      //   56: getfield 32	okhttp3/internal/e/i$a:dbB	Lokhttp3/internal/e/i;
      //   59: invokevirtual 67	okhttp3/internal/e/i:waitForIo	()V
      //   62: goto -43 -> 19
      //   65: astore 6
      //   67: aload_0
      //   68: getfield 32	okhttp3/internal/e/i$a:dbB	Lokhttp3/internal/e/i;
      //   71: getfield 47	okhttp3/internal/e/i:dby	Lokhttp3/internal/e/i$c;
      //   74: invokevirtual 70	okhttp3/internal/e/i$c:exitAndThrowIfTimedOut	()V
      //   77: aload 6
      //   79: athrow
      //   80: astore 6
      //   82: aload 5
      //   84: monitorexit
      //   85: aload 6
      //   87: athrow
      //   88: aload_0
      //   89: getfield 32	okhttp3/internal/e/i$a:dbB	Lokhttp3/internal/e/i;
      //   92: getfield 47	okhttp3/internal/e/i:dby	Lokhttp3/internal/e/i$c;
      //   95: invokevirtual 70	okhttp3/internal/e/i$c:exitAndThrowIfTimedOut	()V
      //   98: aload_0
      //   99: getfield 32	okhttp3/internal/e/i$a:dbB	Lokhttp3/internal/e/i;
      //   102: invokevirtual 73	okhttp3/internal/e/i:checkOutNotClosed	()V
      //   105: aload_0
      //   106: getfield 32	okhttp3/internal/e/i$a:dbB	Lokhttp3/internal/e/i;
      //   109: getfield 56	okhttp3/internal/e/i:bytesLeftInWriteWindow	J
      //   112: aload_0
      //   113: getfield 39	okhttp3/internal/e/i$a:dbA	Ld/c;
      //   116: getfield 76	d/c:size	J
      //   119: invokestatic 82	java/lang/Math:min	(JJ)J
      //   122: lstore_3
      //   123: aload_0
      //   124: getfield 32	okhttp3/internal/e/i$a:dbB	Lokhttp3/internal/e/i;
      //   127: astore 6
      //   129: aload 6
      //   131: aload 6
      //   133: getfield 56	okhttp3/internal/e/i:bytesLeftInWriteWindow	J
      //   136: lload_3
      //   137: lsub
      //   138: putfield 56	okhttp3/internal/e/i:bytesLeftInWriteWindow	J
      //   141: aload 5
      //   143: monitorexit
      //   144: aload_0
      //   145: getfield 32	okhttp3/internal/e/i$a:dbB	Lokhttp3/internal/e/i;
      //   148: getfield 47	okhttp3/internal/e/i:dby	Lokhttp3/internal/e/i$c;
      //   151: invokevirtual 52	okhttp3/internal/e/i$c:enter	()V
      //   154: aload_0
      //   155: getfield 32	okhttp3/internal/e/i$a:dbB	Lokhttp3/internal/e/i;
      //   158: getfield 86	okhttp3/internal/e/i:daV	Lokhttp3/internal/e/g;
      //   161: astore 5
      //   163: aload_0
      //   164: getfield 32	okhttp3/internal/e/i$a:dbB	Lokhttp3/internal/e/i;
      //   167: getfield 90	okhttp3/internal/e/i:id	I
      //   170: istore_2
      //   171: iload_1
      //   172: ifeq +40 -> 212
      //   175: lload_3
      //   176: aload_0
      //   177: getfield 39	okhttp3/internal/e/i$a:dbA	Ld/c;
      //   180: getfield 76	d/c:size	J
      //   183: lcmp
      //   184: ifne +28 -> 212
      //   187: iconst_1
      //   188: istore_1
      //   189: aload 5
      //   191: iload_2
      //   192: iload_1
      //   193: aload_0
      //   194: getfield 39	okhttp3/internal/e/i$a:dbA	Ld/c;
      //   197: lload_3
      //   198: invokevirtual 95	okhttp3/internal/e/g:a	(IZLd/c;J)V
      //   201: aload_0
      //   202: getfield 32	okhttp3/internal/e/i$a:dbB	Lokhttp3/internal/e/i;
      //   205: getfield 47	okhttp3/internal/e/i:dby	Lokhttp3/internal/e/i$c;
      //   208: invokevirtual 70	okhttp3/internal/e/i$c:exitAndThrowIfTimedOut	()V
      //   211: return
      //   212: iconst_0
      //   213: istore_1
      //   214: goto -25 -> 189
      //   217: astore 5
      //   219: aload_0
      //   220: getfield 32	okhttp3/internal/e/i$a:dbB	Lokhttp3/internal/e/i;
      //   223: getfield 47	okhttp3/internal/e/i:dby	Lokhttp3/internal/e/i$c;
      //   226: invokevirtual 70	okhttp3/internal/e/i$c:exitAndThrowIfTimedOut	()V
      //   229: aload 5
      //   231: athrow
      // Local variable table:
      //   start	length	slot	name	signature
      //   0	232	0	this	a
      //   0	232	1	paramBoolean	boolean
      //   170	22	2	i	int
      //   122	76	3	l	long
      //   4	186	5	localObject1	Object
      //   217	13	5	localObject2	Object
      //   65	13	6	localObject3	Object
      //   80	6	6	localObject4	Object
      //   127	5	6	locali	i
      // Exception table:
      //   from	to	target	type
      //   19	62	65	finally
      //   9	19	80	finally
      //   67	80	80	finally
      //   82	85	80	finally
      //   88	144	80	finally
      //   154	171	217	finally
      //   175	187	217	finally
      //   189	201	217	finally
    }
    
    public final t MK()
    {
      return i.this.dby;
    }
    
    public final void b(d.c paramc, long paramLong)
      throws IOException
    {
      assert (!Thread.holdsLock(i.this));
      this.dbA.b(paramc, paramLong);
      while (this.dbA.size >= 16384L) {
        emitFrame(false);
      }
    }
    
    public final void close()
      throws IOException
    {
      assert (!Thread.holdsLock(i.this));
      synchronized (i.this)
      {
        if (this.closed) {
          return;
        }
        if (i.this.dbw.finished) {
          break label113;
        }
        if (this.dbA.size > 0L)
        {
          if (this.dbA.size <= 0L) {
            break label113;
          }
          emitFrame(true);
        }
      }
      i.this.daV.a(i.this.id, true, null, 0L);
      label113:
      synchronized (i.this)
      {
        this.closed = true;
        i.this.daV.dbf.flush();
        i.this.cancelStreamIfNecessary();
        return;
      }
    }
    
    public final void flush()
      throws IOException
    {
      assert (!Thread.holdsLock(i.this));
      synchronized (i.this)
      {
        i.this.checkOutNotClosed();
        if (this.dbA.size > 0L)
        {
          emitFrame(false);
          i.this.daV.dbf.flush();
        }
      }
    }
  }
  
  private final class b
    implements s
  {
    boolean closed;
    private final d.c dbC = new d.c();
    private final d.c dbD = new d.c();
    boolean finished;
    private final long maxByteCount;
    
    static
    {
      if (!i.class.desiredAssertionStatus()) {}
      for (boolean bool = true;; bool = false)
      {
        $assertionsDisabled = bool;
        return;
      }
    }
    
    b(long paramLong)
    {
      this.maxByteCount = paramLong;
    }
    
    /* Error */
    private void waitUntilReadable()
      throws IOException
    {
      // Byte code:
      //   0: aload_0
      //   1: getfield 35	okhttp3/internal/e/i$b:dbB	Lokhttp3/internal/e/i;
      //   4: getfield 53	okhttp3/internal/e/i:dbx	Lokhttp3/internal/e/i$c;
      //   7: invokevirtual 58	okhttp3/internal/e/i$c:enter	()V
      //   10: aload_0
      //   11: getfield 44	okhttp3/internal/e/i$b:dbD	Ld/c;
      //   14: getfield 61	d/c:size	J
      //   17: lconst_0
      //   18: lcmp
      //   19: ifne +50 -> 69
      //   22: aload_0
      //   23: getfield 63	okhttp3/internal/e/i$b:finished	Z
      //   26: ifne +43 -> 69
      //   29: aload_0
      //   30: getfield 65	okhttp3/internal/e/i$b:closed	Z
      //   33: ifne +36 -> 69
      //   36: aload_0
      //   37: getfield 35	okhttp3/internal/e/i$b:dbB	Lokhttp3/internal/e/i;
      //   40: getfield 69	okhttp3/internal/e/i:dbz	Lokhttp3/internal/e/b;
      //   43: ifnonnull +26 -> 69
      //   46: aload_0
      //   47: getfield 35	okhttp3/internal/e/i$b:dbB	Lokhttp3/internal/e/i;
      //   50: invokevirtual 72	okhttp3/internal/e/i:waitForIo	()V
      //   53: goto -43 -> 10
      //   56: astore_1
      //   57: aload_0
      //   58: getfield 35	okhttp3/internal/e/i$b:dbB	Lokhttp3/internal/e/i;
      //   61: getfield 53	okhttp3/internal/e/i:dbx	Lokhttp3/internal/e/i$c;
      //   64: invokevirtual 75	okhttp3/internal/e/i$c:exitAndThrowIfTimedOut	()V
      //   67: aload_1
      //   68: athrow
      //   69: aload_0
      //   70: getfield 35	okhttp3/internal/e/i$b:dbB	Lokhttp3/internal/e/i;
      //   73: getfield 53	okhttp3/internal/e/i:dbx	Lokhttp3/internal/e/i$c;
      //   76: invokevirtual 75	okhttp3/internal/e/i$c:exitAndThrowIfTimedOut	()V
      //   79: return
      // Local variable table:
      //   start	length	slot	name	signature
      //   0	80	0	this	b
      //   56	12	1	localObject	Object
      // Exception table:
      //   from	to	target	type
      //   10	53	56	finally
    }
    
    public final t MK()
    {
      return i.this.dbx;
    }
    
    public final long a(d.c arg1, long paramLong)
      throws IOException
    {
      if (paramLong < 0L) {
        throw new IllegalArgumentException("byteCount < 0: " + paramLong);
      }
      synchronized (i.this)
      {
        waitUntilReadable();
        if (this.closed) {
          throw new IOException("stream closed");
        }
      }
      if (i.this.dbz != null) {
        throw new n(i.this.dbz);
      }
      if (this.dbD.size == 0L) {
        return -1L;
      }
      paramLong = this.dbD.a(???, Math.min(paramLong, this.dbD.size));
      ??? = i.this;
      ???.unacknowledgedBytesRead += paramLong;
      if (i.this.unacknowledgedBytesRead >= i.this.daV.dbd.getInitialWindowSize() / 2)
      {
        i.this.daV.writeWindowUpdateLater(i.this.id, i.this.unacknowledgedBytesRead);
        i.this.unacknowledgedBytesRead = 0L;
      }
      synchronized (i.this.daV)
      {
        ??? = i.this.daV;
        ((g)???).unacknowledgedBytesRead += paramLong;
        if (i.this.daV.unacknowledgedBytesRead >= i.this.daV.dbd.getInitialWindowSize() / 2)
        {
          i.this.daV.writeWindowUpdateLater(0, i.this.daV.unacknowledgedBytesRead);
          i.this.daV.unacknowledgedBytesRead = 0L;
        }
        return paramLong;
      }
    }
    
    final void a(e parame, long paramLong)
      throws IOException
    {
      long l = paramLong;
      if (!$assertionsDisabled)
      {
        l = paramLong;
        if (Thread.holdsLock(i.this)) {
          throw new AssertionError();
        }
      }
      for (;;)
      {
        l -= paramLong;
        synchronized (i.this)
        {
          if (this.dbD.size == 0L)
          {
            i = 1;
            this.dbD.a(this.dbC);
            if (i != 0) {
              i.this.notifyAll();
            }
            if (l > 0L) {}
            boolean bool;
            synchronized (i.this)
            {
              bool = this.finished;
              if (this.dbD.size + l > this.maxByteCount)
              {
                i = 1;
                if (i != 0)
                {
                  parame.ah(l);
                  i.this.c(b.dar);
                }
              }
              else
              {
                i = 0;
              }
            }
            if (bool)
            {
              parame.ah(l);
              return;
            }
            paramLong = parame.a(this.dbC, l);
            if (paramLong != -1L) {
              continue;
            }
            throw new EOFException();
          }
          int i = 0;
        }
      }
    }
    
    public final void close()
      throws IOException
    {
      synchronized (i.this)
      {
        this.closed = true;
        this.dbD.clear();
        i.this.notifyAll();
        i.this.cancelStreamIfNecessary();
        return;
      }
    }
  }
  
  final class c
    extends a
  {
    c() {}
    
    public final void exitAndThrowIfTimedOut()
      throws IOException
    {
      if (exit()) {
        throw newTimeoutException(null);
      }
    }
    
    protected final IOException newTimeoutException(IOException paramIOException)
    {
      SocketTimeoutException localSocketTimeoutException = new SocketTimeoutException("timeout");
      if (paramIOException != null) {
        localSocketTimeoutException.initCause(paramIOException);
      }
      return localSocketTimeoutException;
    }
    
    protected final void timedOut()
    {
      i.this.c(b.dat);
    }
  }
}


/* Location:              /home/qerwtr546/Documents/Vent Source/dex2jar-2.0/classes-dex2jar.jar!/okhttp3/internal/e/i.class
 * Java compiler version: 6 (50.0)
 * JD-Core Version:       0.7.1
 */