package com.google.android.gms.internal;

public final class ag
  implements z
{
  private final String aLm = null;
  
  public ag()
  {
    this((byte)0);
  }
  
  private ag(byte paramByte) {}
  
  /* Error */
  public final void bp(String paramString)
  {
    // Byte code:
    //   0: aconst_null
    //   1: astore 4
    //   3: aload_1
    //   4: invokestatic 32	java/lang/String:valueOf	(Ljava/lang/Object;)Ljava/lang/String;
    //   7: astore_3
    //   8: aload_3
    //   9: invokevirtual 36	java/lang/String:length	()I
    //   12: ifeq +233 -> 245
    //   15: ldc 38
    //   17: aload_3
    //   18: invokevirtual 42	java/lang/String:concat	(Ljava/lang/String;)Ljava/lang/String;
    //   21: astore_3
    //   22: aload_3
    //   23: invokestatic 47	com/google/android/gms/internal/af:br	(Ljava/lang/String;)V
    //   26: new 49	java/net/URL
    //   29: dup
    //   30: aload_1
    //   31: invokespecial 51	java/net/URL:<init>	(Ljava/lang/String;)V
    //   34: invokevirtual 55	java/net/URL:openConnection	()Ljava/net/URLConnection;
    //   37: checkcast 57	java/net/HttpURLConnection
    //   40: astore 5
    //   42: invokestatic 63	com/google/android/gms/internal/of:tj	()Lcom/google/android/gms/internal/w;
    //   45: pop
    //   46: aload 5
    //   48: aload_0
    //   49: getfield 18	com/google/android/gms/internal/ag:aLm	Ljava/lang/String;
    //   52: invokestatic 69	com/google/android/gms/internal/w:a	(Ljava/net/HttpURLConnection;Ljava/lang/String;)V
    //   55: new 71	com/google/android/gms/internal/aa
    //   58: dup
    //   59: invokespecial 72	com/google/android/gms/internal/aa:<init>	()V
    //   62: astore 6
    //   64: invokestatic 76	com/google/android/gms/internal/aa:isEnabled	()Z
    //   67: ifeq +55 -> 122
    //   70: aload 5
    //   72: invokevirtual 80	java/net/HttpURLConnection:getRequestProperties	()Ljava/util/Map;
    //   75: ifnonnull +239 -> 314
    //   78: aconst_null
    //   79: astore_3
    //   80: aload 6
    //   82: ldc 82
    //   84: new 84	com/google/android/gms/internal/ab
    //   87: dup
    //   88: new 28	java/lang/String
    //   91: dup
    //   92: aload 5
    //   94: invokevirtual 88	java/net/HttpURLConnection:getURL	()Ljava/net/URL;
    //   97: invokevirtual 92	java/net/URL:toString	()Ljava/lang/String;
    //   100: invokespecial 93	java/lang/String:<init>	(Ljava/lang/String;)V
    //   103: new 28	java/lang/String
    //   106: dup
    //   107: aload 5
    //   109: invokevirtual 96	java/net/HttpURLConnection:getRequestMethod	()Ljava/lang/String;
    //   112: invokespecial 93	java/lang/String:<init>	(Ljava/lang/String;)V
    //   115: aload_3
    //   116: invokespecial 99	com/google/android/gms/internal/ab:<init>	(Ljava/lang/String;Ljava/lang/String;Ljava/util/Map;)V
    //   119: invokevirtual 102	com/google/android/gms/internal/aa:a	(Ljava/lang/String;Lcom/google/android/gms/internal/ae;)V
    //   122: aload 5
    //   124: invokevirtual 105	java/net/HttpURLConnection:getResponseCode	()I
    //   127: istore_2
    //   128: invokestatic 76	com/google/android/gms/internal/aa:isEnabled	()Z
    //   131: ifeq +381 -> 512
    //   134: aload 5
    //   136: invokevirtual 108	java/net/HttpURLConnection:getHeaderFields	()Ljava/util/Map;
    //   139: ifnonnull +255 -> 394
    //   142: aconst_null
    //   143: astore_3
    //   144: aload 6
    //   146: ldc 110
    //   148: new 112	com/google/android/gms/internal/ac
    //   151: dup
    //   152: iload_2
    //   153: aload_3
    //   154: invokespecial 115	com/google/android/gms/internal/ac:<init>	(ILjava/util/Map;)V
    //   157: invokevirtual 102	com/google/android/gms/internal/aa:a	(Ljava/lang/String;Lcom/google/android/gms/internal/ae;)V
    //   160: iload_2
    //   161: sipush 200
    //   164: if_icmplt +10 -> 174
    //   167: iload_2
    //   168: sipush 300
    //   171: if_icmplt +341 -> 512
    //   174: aload 5
    //   176: invokevirtual 118	java/net/HttpURLConnection:getResponseMessage	()Ljava/lang/String;
    //   179: astore_3
    //   180: aload 6
    //   182: ldc 120
    //   184: new 122	com/google/android/gms/internal/ad
    //   187: dup
    //   188: aload_3
    //   189: invokespecial 123	com/google/android/gms/internal/ad:<init>	(Ljava/lang/String;)V
    //   192: invokevirtual 102	com/google/android/gms/internal/aa:a	(Ljava/lang/String;Lcom/google/android/gms/internal/ae;)V
    //   195: goto +317 -> 512
    //   198: new 125	java/lang/StringBuilder
    //   201: dup
    //   202: aload_1
    //   203: invokestatic 32	java/lang/String:valueOf	(Ljava/lang/Object;)Ljava/lang/String;
    //   206: invokevirtual 36	java/lang/String:length	()I
    //   209: bipush 65
    //   211: iadd
    //   212: invokespecial 128	java/lang/StringBuilder:<init>	(I)V
    //   215: ldc -126
    //   217: invokevirtual 134	java/lang/StringBuilder:append	(Ljava/lang/String;)Ljava/lang/StringBuilder;
    //   220: iload_2
    //   221: invokevirtual 137	java/lang/StringBuilder:append	(I)Ljava/lang/StringBuilder;
    //   224: ldc -117
    //   226: invokevirtual 134	java/lang/StringBuilder:append	(Ljava/lang/String;)Ljava/lang/StringBuilder;
    //   229: aload_1
    //   230: invokevirtual 134	java/lang/StringBuilder:append	(Ljava/lang/String;)Ljava/lang/StringBuilder;
    //   233: invokevirtual 140	java/lang/StringBuilder:toString	()Ljava/lang/String;
    //   236: invokestatic 143	com/google/android/gms/internal/af:bt	(Ljava/lang/String;)V
    //   239: aload 5
    //   241: invokevirtual 146	java/net/HttpURLConnection:disconnect	()V
    //   244: return
    //   245: new 28	java/lang/String
    //   248: dup
    //   249: ldc 38
    //   251: invokespecial 93	java/lang/String:<init>	(Ljava/lang/String;)V
    //   254: astore_3
    //   255: goto -233 -> 22
    //   258: astore_3
    //   259: aload_3
    //   260: invokevirtual 149	java/lang/IndexOutOfBoundsException:getMessage	()Ljava/lang/String;
    //   263: astore_3
    //   264: new 125	java/lang/StringBuilder
    //   267: dup
    //   268: aload_1
    //   269: invokestatic 32	java/lang/String:valueOf	(Ljava/lang/Object;)Ljava/lang/String;
    //   272: invokevirtual 36	java/lang/String:length	()I
    //   275: bipush 32
    //   277: iadd
    //   278: aload_3
    //   279: invokestatic 32	java/lang/String:valueOf	(Ljava/lang/Object;)Ljava/lang/String;
    //   282: invokevirtual 36	java/lang/String:length	()I
    //   285: iadd
    //   286: invokespecial 128	java/lang/StringBuilder:<init>	(I)V
    //   289: ldc -105
    //   291: invokevirtual 134	java/lang/StringBuilder:append	(Ljava/lang/String;)Ljava/lang/StringBuilder;
    //   294: aload_1
    //   295: invokevirtual 134	java/lang/StringBuilder:append	(Ljava/lang/String;)Ljava/lang/StringBuilder;
    //   298: ldc -103
    //   300: invokevirtual 134	java/lang/StringBuilder:append	(Ljava/lang/String;)Ljava/lang/StringBuilder;
    //   303: aload_3
    //   304: invokevirtual 134	java/lang/StringBuilder:append	(Ljava/lang/String;)Ljava/lang/StringBuilder;
    //   307: invokevirtual 140	java/lang/StringBuilder:toString	()Ljava/lang/String;
    //   310: invokestatic 143	com/google/android/gms/internal/af:bt	(Ljava/lang/String;)V
    //   313: return
    //   314: new 155	java/util/HashMap
    //   317: dup
    //   318: aload 5
    //   320: invokevirtual 80	java/net/HttpURLConnection:getRequestProperties	()Ljava/util/Map;
    //   323: invokespecial 158	java/util/HashMap:<init>	(Ljava/util/Map;)V
    //   326: astore_3
    //   327: goto -247 -> 80
    //   330: astore_3
    //   331: aload 5
    //   333: invokevirtual 146	java/net/HttpURLConnection:disconnect	()V
    //   336: aload_3
    //   337: athrow
    //   338: astore_3
    //   339: aload_3
    //   340: invokevirtual 159	java/io/IOException:getMessage	()Ljava/lang/String;
    //   343: astore_3
    //   344: new 125	java/lang/StringBuilder
    //   347: dup
    //   348: aload_1
    //   349: invokestatic 32	java/lang/String:valueOf	(Ljava/lang/Object;)Ljava/lang/String;
    //   352: invokevirtual 36	java/lang/String:length	()I
    //   355: bipush 27
    //   357: iadd
    //   358: aload_3
    //   359: invokestatic 32	java/lang/String:valueOf	(Ljava/lang/Object;)Ljava/lang/String;
    //   362: invokevirtual 36	java/lang/String:length	()I
    //   365: iadd
    //   366: invokespecial 128	java/lang/StringBuilder:<init>	(I)V
    //   369: ldc -95
    //   371: invokevirtual 134	java/lang/StringBuilder:append	(Ljava/lang/String;)Ljava/lang/StringBuilder;
    //   374: aload_1
    //   375: invokevirtual 134	java/lang/StringBuilder:append	(Ljava/lang/String;)Ljava/lang/StringBuilder;
    //   378: ldc -103
    //   380: invokevirtual 134	java/lang/StringBuilder:append	(Ljava/lang/String;)Ljava/lang/StringBuilder;
    //   383: aload_3
    //   384: invokevirtual 134	java/lang/StringBuilder:append	(Ljava/lang/String;)Ljava/lang/StringBuilder;
    //   387: invokevirtual 140	java/lang/StringBuilder:toString	()Ljava/lang/String;
    //   390: invokestatic 143	com/google/android/gms/internal/af:bt	(Ljava/lang/String;)V
    //   393: return
    //   394: new 155	java/util/HashMap
    //   397: dup
    //   398: aload 5
    //   400: invokevirtual 108	java/net/HttpURLConnection:getHeaderFields	()Ljava/util/Map;
    //   403: invokespecial 158	java/util/HashMap:<init>	(Ljava/util/Map;)V
    //   406: astore_3
    //   407: goto -263 -> 144
    //   410: astore_3
    //   411: aload_3
    //   412: invokevirtual 159	java/io/IOException:getMessage	()Ljava/lang/String;
    //   415: invokestatic 32	java/lang/String:valueOf	(Ljava/lang/Object;)Ljava/lang/String;
    //   418: astore_3
    //   419: aload_3
    //   420: invokevirtual 36	java/lang/String:length	()I
    //   423: ifeq +20 -> 443
    //   426: ldc -93
    //   428: aload_3
    //   429: invokevirtual 42	java/lang/String:concat	(Ljava/lang/String;)Ljava/lang/String;
    //   432: astore_3
    //   433: aload_3
    //   434: invokestatic 143	com/google/android/gms/internal/af:bt	(Ljava/lang/String;)V
    //   437: aload 4
    //   439: astore_3
    //   440: goto -260 -> 180
    //   443: new 28	java/lang/String
    //   446: dup
    //   447: ldc -93
    //   449: invokespecial 93	java/lang/String:<init>	(Ljava/lang/String;)V
    //   452: astore_3
    //   453: goto -20 -> 433
    //   456: astore_3
    //   457: aload_3
    //   458: invokevirtual 164	java/lang/RuntimeException:getMessage	()Ljava/lang/String;
    //   461: astore_3
    //   462: new 125	java/lang/StringBuilder
    //   465: dup
    //   466: aload_1
    //   467: invokestatic 32	java/lang/String:valueOf	(Ljava/lang/Object;)Ljava/lang/String;
    //   470: invokevirtual 36	java/lang/String:length	()I
    //   473: bipush 27
    //   475: iadd
    //   476: aload_3
    //   477: invokestatic 32	java/lang/String:valueOf	(Ljava/lang/Object;)Ljava/lang/String;
    //   480: invokevirtual 36	java/lang/String:length	()I
    //   483: iadd
    //   484: invokespecial 128	java/lang/StringBuilder:<init>	(I)V
    //   487: ldc -95
    //   489: invokevirtual 134	java/lang/StringBuilder:append	(Ljava/lang/String;)Ljava/lang/StringBuilder;
    //   492: aload_1
    //   493: invokevirtual 134	java/lang/StringBuilder:append	(Ljava/lang/String;)Ljava/lang/StringBuilder;
    //   496: ldc -103
    //   498: invokevirtual 134	java/lang/StringBuilder:append	(Ljava/lang/String;)Ljava/lang/StringBuilder;
    //   501: aload_3
    //   502: invokevirtual 134	java/lang/StringBuilder:append	(Ljava/lang/String;)Ljava/lang/StringBuilder;
    //   505: invokevirtual 140	java/lang/StringBuilder:toString	()Ljava/lang/String;
    //   508: invokestatic 143	com/google/android/gms/internal/af:bt	(Ljava/lang/String;)V
    //   511: return
    //   512: iload_2
    //   513: sipush 200
    //   516: if_icmplt -318 -> 198
    //   519: iload_2
    //   520: sipush 300
    //   523: if_icmplt -284 -> 239
    //   526: goto -328 -> 198
    // Local variable table:
    //   start	length	slot	name	signature
    //   0	529	0	this	ag
    //   0	529	1	paramString	String
    //   127	397	2	i	int
    //   7	248	3	str1	String
    //   258	2	3	localIndexOutOfBoundsException	IndexOutOfBoundsException
    //   263	64	3	localObject1	Object
    //   330	7	3	localObject2	Object
    //   338	2	3	localIOException1	java.io.IOException
    //   343	64	3	localObject3	Object
    //   410	2	3	localIOException2	java.io.IOException
    //   418	35	3	localObject4	Object
    //   456	2	3	localRuntimeException	RuntimeException
    //   461	41	3	str2	String
    //   1	437	4	localObject5	Object
    //   40	359	5	localHttpURLConnection	java.net.HttpURLConnection
    //   62	119	6	localaa	aa
    // Exception table:
    //   from	to	target	type
    //   3	22	258	java/lang/IndexOutOfBoundsException
    //   22	42	258	java/lang/IndexOutOfBoundsException
    //   239	244	258	java/lang/IndexOutOfBoundsException
    //   245	255	258	java/lang/IndexOutOfBoundsException
    //   331	338	258	java/lang/IndexOutOfBoundsException
    //   42	78	330	finally
    //   80	122	330	finally
    //   122	142	330	finally
    //   144	160	330	finally
    //   174	180	330	finally
    //   180	195	330	finally
    //   198	239	330	finally
    //   314	327	330	finally
    //   394	407	330	finally
    //   411	433	330	finally
    //   433	437	330	finally
    //   443	453	330	finally
    //   3	22	338	java/io/IOException
    //   22	42	338	java/io/IOException
    //   239	244	338	java/io/IOException
    //   245	255	338	java/io/IOException
    //   331	338	338	java/io/IOException
    //   174	180	410	java/io/IOException
    //   3	22	456	java/lang/RuntimeException
    //   22	42	456	java/lang/RuntimeException
    //   239	244	456	java/lang/RuntimeException
    //   245	255	456	java/lang/RuntimeException
    //   331	338	456	java/lang/RuntimeException
  }
}


/* Location:              /home/qerwtr546/Documents/Vent Source/dex2jar-2.0/classes-dex2jar.jar!/com/google/android/gms/internal/ag.class
 * Java compiler version: 6 (50.0)
 * JD-Core Version:       0.7.1
 */