package com.google.android.gms.internal;

import com.google.android.gms.common.internal.ae;
import java.net.URL;
import java.util.Map;

final class hi
  implements Runnable
{
  private final byte[] aTw;
  private final hg aTx;
  private final Map<String, String> aTy;
  private final String packageName;
  private final URL url;
  
  public hi(String paramString, URL paramURL, byte[] paramArrayOfByte, Map<String, String> paramMap, hg paramhg)
  {
    ae.bf(paramURL);
    ae.E(paramArrayOfByte);
    Object localObject;
    ae.E(localObject);
    this.url = paramArrayOfByte;
    this.aTw = paramMap;
    this.aTx = ((hg)localObject);
    this.packageName = paramURL;
    this.aTy = paramhg;
  }
  
  /* Error */
  public final void run()
  {
    // Byte code:
    //   0: aload_0
    //   1: getfield 23	com/google/android/gms/internal/hi:aTz	Lcom/google/android/gms/internal/hf;
    //   4: invokevirtual 57	com/google/android/gms/internal/ix:qz	()V
    //   7: aconst_null
    //   8: astore 7
    //   10: iconst_0
    //   11: istore_2
    //   12: iconst_0
    //   13: istore 4
    //   15: iconst_0
    //   16: istore_3
    //   17: iconst_0
    //   18: istore_1
    //   19: aconst_null
    //   20: astore 9
    //   22: aconst_null
    //   23: astore 10
    //   25: aconst_null
    //   26: astore 11
    //   28: aconst_null
    //   29: astore 5
    //   31: aload_0
    //   32: getfield 23	com/google/android/gms/internal/hi:aTz	Lcom/google/android/gms/internal/hf;
    //   35: astore 6
    //   37: aload_0
    //   38: getfield 38	com/google/android/gms/internal/hi:url	Ljava/net/URL;
    //   41: invokevirtual 63	java/net/URL:openConnection	()Ljava/net/URLConnection;
    //   44: astore 8
    //   46: aload 8
    //   48: instanceof 65
    //   51: ifne +74 -> 125
    //   54: new 52	java/io/IOException
    //   57: dup
    //   58: ldc 67
    //   60: invokespecial 70	java/io/IOException:<init>	(Ljava/lang/String;)V
    //   63: athrow
    //   64: astore 6
    //   66: aconst_null
    //   67: astore 7
    //   69: aconst_null
    //   70: astore 8
    //   72: aload 7
    //   74: ifnull +8 -> 82
    //   77: aload 7
    //   79: invokevirtual 75	java/io/OutputStream:close	()V
    //   82: aload 8
    //   84: ifnull +8 -> 92
    //   87: aload 8
    //   89: invokevirtual 78	java/net/HttpURLConnection:disconnect	()V
    //   92: aload_0
    //   93: getfield 23	com/google/android/gms/internal/hi:aTz	Lcom/google/android/gms/internal/hf;
    //   96: invokevirtual 82	com/google/android/gms/internal/ix:qO	()Lcom/google/android/gms/internal/hu;
    //   99: new 84	com/google/android/gms/internal/hh
    //   102: dup
    //   103: aload_0
    //   104: getfield 44	com/google/android/gms/internal/hi:packageName	Ljava/lang/String;
    //   107: aload_0
    //   108: getfield 42	com/google/android/gms/internal/hi:aTx	Lcom/google/android/gms/internal/hg;
    //   111: iload_1
    //   112: aload 6
    //   114: aconst_null
    //   115: aload 5
    //   117: iconst_0
    //   118: invokespecial 87	com/google/android/gms/internal/hh:<init>	(Ljava/lang/String;Lcom/google/android/gms/internal/hg;ILjava/lang/Throwable;[BLjava/util/Map;B)V
    //   121: invokevirtual 93	com/google/android/gms/internal/hu:i	(Ljava/lang/Runnable;)V
    //   124: return
    //   125: aload 6
    //   127: getfield 99	com/google/android/gms/internal/hf:sslSocketFactory	Ljavax/net/ssl/SSLSocketFactory;
    //   130: ifnull +24 -> 154
    //   133: aload 8
    //   135: instanceof 101
    //   138: ifeq +16 -> 154
    //   141: aload 8
    //   143: checkcast 101	javax/net/ssl/HttpsURLConnection
    //   146: aload 6
    //   148: getfield 99	com/google/android/gms/internal/hf:sslSocketFactory	Ljavax/net/ssl/SSLSocketFactory;
    //   151: invokevirtual 105	javax/net/ssl/HttpsURLConnection:setSSLSocketFactory	(Ljavax/net/ssl/SSLSocketFactory;)V
    //   154: aload 8
    //   156: checkcast 65	java/net/HttpURLConnection
    //   159: astore 8
    //   161: aload 8
    //   163: iconst_0
    //   164: invokevirtual 109	java/net/HttpURLConnection:setDefaultUseCaches	(Z)V
    //   167: aload 8
    //   169: ldc 110
    //   171: invokevirtual 114	java/net/HttpURLConnection:setConnectTimeout	(I)V
    //   174: aload 8
    //   176: ldc 115
    //   178: invokevirtual 118	java/net/HttpURLConnection:setReadTimeout	(I)V
    //   181: aload 8
    //   183: iconst_0
    //   184: invokevirtual 121	java/net/HttpURLConnection:setInstanceFollowRedirects	(Z)V
    //   187: aload 8
    //   189: iconst_1
    //   190: invokevirtual 124	java/net/HttpURLConnection:setDoInput	(Z)V
    //   193: aload_0
    //   194: getfield 46	com/google/android/gms/internal/hi:aTy	Ljava/util/Map;
    //   197: ifnull +69 -> 266
    //   200: aload_0
    //   201: getfield 46	com/google/android/gms/internal/hi:aTy	Ljava/util/Map;
    //   204: invokeinterface 130 1 0
    //   209: invokeinterface 136 1 0
    //   214: astore 6
    //   216: aload 6
    //   218: invokeinterface 142 1 0
    //   223: ifeq +43 -> 266
    //   226: aload 6
    //   228: invokeinterface 146 1 0
    //   233: checkcast 148	java/util/Map$Entry
    //   236: astore 12
    //   238: aload 8
    //   240: aload 12
    //   242: invokeinterface 151 1 0
    //   247: checkcast 153	java/lang/String
    //   250: aload 12
    //   252: invokeinterface 156 1 0
    //   257: checkcast 153	java/lang/String
    //   260: invokevirtual 160	java/net/HttpURLConnection:addRequestProperty	(Ljava/lang/String;Ljava/lang/String;)V
    //   263: goto -47 -> 216
    //   266: aload_0
    //   267: getfield 40	com/google/android/gms/internal/hi:aTw	[B
    //   270: ifnull +378 -> 648
    //   273: aload_0
    //   274: getfield 23	com/google/android/gms/internal/hi:aTz	Lcom/google/android/gms/internal/hf;
    //   277: invokevirtual 164	com/google/android/gms/internal/ix:qL	()Lcom/google/android/gms/internal/le;
    //   280: aload_0
    //   281: getfield 40	com/google/android/gms/internal/hi:aTw	[B
    //   284: invokevirtual 170	com/google/android/gms/internal/le:n	([B)[B
    //   287: astore 12
    //   289: aload_0
    //   290: getfield 23	com/google/android/gms/internal/hi:aTz	Lcom/google/android/gms/internal/hf;
    //   293: invokevirtual 174	com/google/android/gms/internal/ix:qP	()Lcom/google/android/gms/internal/hb;
    //   296: getfield 180	com/google/android/gms/internal/hb:aTi	Lcom/google/android/gms/internal/hd;
    //   299: ldc -74
    //   301: aload 12
    //   303: arraylength
    //   304: invokestatic 188	java/lang/Integer:valueOf	(I)Ljava/lang/Integer;
    //   307: invokevirtual 194	com/google/android/gms/internal/hd:j	(Ljava/lang/String;Ljava/lang/Object;)V
    //   310: aload 8
    //   312: iconst_1
    //   313: invokevirtual 197	java/net/HttpURLConnection:setDoOutput	(Z)V
    //   316: aload 8
    //   318: ldc -57
    //   320: ldc -55
    //   322: invokevirtual 160	java/net/HttpURLConnection:addRequestProperty	(Ljava/lang/String;Ljava/lang/String;)V
    //   325: aload 8
    //   327: aload 12
    //   329: arraylength
    //   330: invokevirtual 204	java/net/HttpURLConnection:setFixedLengthStreamingMode	(I)V
    //   333: aload 8
    //   335: invokevirtual 207	java/net/HttpURLConnection:connect	()V
    //   338: aload 8
    //   340: invokevirtual 211	java/net/HttpURLConnection:getOutputStream	()Ljava/io/OutputStream;
    //   343: astore 6
    //   345: aload 6
    //   347: astore 7
    //   349: iload_3
    //   350: istore_1
    //   351: aload 11
    //   353: astore 5
    //   355: aload 6
    //   357: aload 12
    //   359: invokevirtual 215	java/io/OutputStream:write	([B)V
    //   362: aload 6
    //   364: astore 7
    //   366: iload_3
    //   367: istore_1
    //   368: aload 11
    //   370: astore 5
    //   372: aload 6
    //   374: invokevirtual 75	java/io/OutputStream:close	()V
    //   377: aconst_null
    //   378: astore 12
    //   380: iload 4
    //   382: istore_2
    //   383: aload 10
    //   385: astore 6
    //   387: aload 12
    //   389: astore 7
    //   391: iload_3
    //   392: istore_1
    //   393: aload 11
    //   395: astore 5
    //   397: aload 8
    //   399: invokevirtual 219	java/net/HttpURLConnection:getResponseCode	()I
    //   402: istore_3
    //   403: iload_3
    //   404: istore_2
    //   405: aload 10
    //   407: astore 6
    //   409: aload 12
    //   411: astore 7
    //   413: iload_3
    //   414: istore_1
    //   415: aload 11
    //   417: astore 5
    //   419: aload 8
    //   421: invokevirtual 223	java/net/HttpURLConnection:getHeaderFields	()Ljava/util/Map;
    //   424: astore 9
    //   426: iload_3
    //   427: istore_2
    //   428: aload 9
    //   430: astore 6
    //   432: aload 12
    //   434: astore 7
    //   436: iload_3
    //   437: istore_1
    //   438: aload 9
    //   440: astore 5
    //   442: aload 8
    //   444: invokestatic 227	com/google/android/gms/internal/hf:b	(Ljava/net/HttpURLConnection;)[B
    //   447: astore 10
    //   449: aload 8
    //   451: ifnull +8 -> 459
    //   454: aload 8
    //   456: invokevirtual 78	java/net/HttpURLConnection:disconnect	()V
    //   459: aload_0
    //   460: getfield 23	com/google/android/gms/internal/hi:aTz	Lcom/google/android/gms/internal/hf;
    //   463: invokevirtual 82	com/google/android/gms/internal/ix:qO	()Lcom/google/android/gms/internal/hu;
    //   466: new 84	com/google/android/gms/internal/hh
    //   469: dup
    //   470: aload_0
    //   471: getfield 44	com/google/android/gms/internal/hi:packageName	Ljava/lang/String;
    //   474: aload_0
    //   475: getfield 42	com/google/android/gms/internal/hi:aTx	Lcom/google/android/gms/internal/hg;
    //   478: iload_3
    //   479: aconst_null
    //   480: aload 10
    //   482: aload 9
    //   484: iconst_0
    //   485: invokespecial 87	com/google/android/gms/internal/hh:<init>	(Ljava/lang/String;Lcom/google/android/gms/internal/hg;ILjava/lang/Throwable;[BLjava/util/Map;B)V
    //   488: invokevirtual 93	com/google/android/gms/internal/hu:i	(Ljava/lang/Runnable;)V
    //   491: return
    //   492: astore 7
    //   494: aload_0
    //   495: getfield 23	com/google/android/gms/internal/hi:aTz	Lcom/google/android/gms/internal/hf;
    //   498: invokevirtual 174	com/google/android/gms/internal/ix:qP	()Lcom/google/android/gms/internal/hb;
    //   501: getfield 230	com/google/android/gms/internal/hb:aTa	Lcom/google/android/gms/internal/hd;
    //   504: ldc -24
    //   506: aload_0
    //   507: getfield 44	com/google/android/gms/internal/hi:packageName	Ljava/lang/String;
    //   510: invokestatic 236	com/google/android/gms/internal/hb:ck	(Ljava/lang/String;)Ljava/lang/Object;
    //   513: aload 7
    //   515: invokevirtual 240	com/google/android/gms/internal/hd:e	(Ljava/lang/String;Ljava/lang/Object;Ljava/lang/Object;)V
    //   518: goto -436 -> 82
    //   521: astore 5
    //   523: aconst_null
    //   524: astore 8
    //   526: aload 9
    //   528: astore 6
    //   530: aload 7
    //   532: ifnull +8 -> 540
    //   535: aload 7
    //   537: invokevirtual 75	java/io/OutputStream:close	()V
    //   540: aload 8
    //   542: ifnull +8 -> 550
    //   545: aload 8
    //   547: invokevirtual 78	java/net/HttpURLConnection:disconnect	()V
    //   550: aload_0
    //   551: getfield 23	com/google/android/gms/internal/hi:aTz	Lcom/google/android/gms/internal/hf;
    //   554: invokevirtual 82	com/google/android/gms/internal/ix:qO	()Lcom/google/android/gms/internal/hu;
    //   557: new 84	com/google/android/gms/internal/hh
    //   560: dup
    //   561: aload_0
    //   562: getfield 44	com/google/android/gms/internal/hi:packageName	Ljava/lang/String;
    //   565: aload_0
    //   566: getfield 42	com/google/android/gms/internal/hi:aTx	Lcom/google/android/gms/internal/hg;
    //   569: iload_2
    //   570: aconst_null
    //   571: aconst_null
    //   572: aload 6
    //   574: iconst_0
    //   575: invokespecial 87	com/google/android/gms/internal/hh:<init>	(Ljava/lang/String;Lcom/google/android/gms/internal/hg;ILjava/lang/Throwable;[BLjava/util/Map;B)V
    //   578: invokevirtual 93	com/google/android/gms/internal/hu:i	(Ljava/lang/Runnable;)V
    //   581: aload 5
    //   583: athrow
    //   584: astore 7
    //   586: aload_0
    //   587: getfield 23	com/google/android/gms/internal/hi:aTz	Lcom/google/android/gms/internal/hf;
    //   590: invokevirtual 174	com/google/android/gms/internal/ix:qP	()Lcom/google/android/gms/internal/hb;
    //   593: getfield 230	com/google/android/gms/internal/hb:aTa	Lcom/google/android/gms/internal/hd;
    //   596: ldc -24
    //   598: aload_0
    //   599: getfield 44	com/google/android/gms/internal/hi:packageName	Ljava/lang/String;
    //   602: invokestatic 236	com/google/android/gms/internal/hb:ck	(Ljava/lang/String;)Ljava/lang/Object;
    //   605: aload 7
    //   607: invokevirtual 240	com/google/android/gms/internal/hd:e	(Ljava/lang/String;Ljava/lang/Object;Ljava/lang/Object;)V
    //   610: goto -70 -> 540
    //   613: astore 5
    //   615: aload 9
    //   617: astore 6
    //   619: goto -89 -> 530
    //   622: astore 5
    //   624: aload 6
    //   626: astore 7
    //   628: aload 9
    //   630: astore 6
    //   632: goto -102 -> 530
    //   635: astore 5
    //   637: aconst_null
    //   638: astore 7
    //   640: goto -110 -> 530
    //   643: astore 6
    //   645: goto -573 -> 72
    //   648: goto -271 -> 377
    //   651: astore 6
    //   653: aconst_null
    //   654: astore 7
    //   656: goto -584 -> 72
    // Local variable table:
    //   start	length	slot	name	signature
    //   0	659	0	this	hi
    //   18	420	1	i	int
    //   11	559	2	j	int
    //   16	463	3	k	int
    //   13	368	4	m	int
    //   29	412	5	localObject1	Object
    //   521	61	5	localObject2	Object
    //   613	1	5	localObject3	Object
    //   622	1	5	localObject4	Object
    //   635	1	5	localObject5	Object
    //   35	1	6	localhf	hf
    //   64	83	6	localIOException1	java.io.IOException
    //   214	417	6	localObject6	Object
    //   643	1	6	localIOException2	java.io.IOException
    //   651	1	6	localIOException3	java.io.IOException
    //   8	427	7	localObject7	Object
    //   492	44	7	localIOException4	java.io.IOException
    //   584	22	7	localIOException5	java.io.IOException
    //   626	29	7	localObject8	Object
    //   44	502	8	localObject9	Object
    //   20	609	9	localMap	Map
    //   23	458	10	arrayOfByte	byte[]
    //   26	390	11	localObject10	Object
    //   236	197	12	localObject11	Object
    // Exception table:
    //   from	to	target	type
    //   31	64	64	java/io/IOException
    //   125	154	64	java/io/IOException
    //   154	193	64	java/io/IOException
    //   77	82	492	java/io/IOException
    //   31	64	521	finally
    //   125	154	521	finally
    //   154	193	521	finally
    //   535	540	584	java/io/IOException
    //   193	216	613	finally
    //   216	263	613	finally
    //   266	345	613	finally
    //   355	362	622	finally
    //   372	377	622	finally
    //   397	403	635	finally
    //   419	426	635	finally
    //   442	449	635	finally
    //   355	362	643	java/io/IOException
    //   372	377	643	java/io/IOException
    //   397	403	643	java/io/IOException
    //   419	426	643	java/io/IOException
    //   442	449	643	java/io/IOException
    //   193	216	651	java/io/IOException
    //   216	263	651	java/io/IOException
    //   266	345	651	java/io/IOException
  }
}


/* Location:              /home/qerwtr546/Documents/Vent Source/dex2jar-2.0/classes-dex2jar.jar!/com/google/android/gms/internal/hi.class
 * Java compiler version: 6 (50.0)
 * JD-Core Version:       0.7.1
 */