package com.firebase.jobdispatcher;

import android.os.Binder;
import android.os.Bundle;
import android.os.IBinder;
import android.os.IInterface;
import android.os.Parcel;
import android.os.Parcelable.Creator;
import android.os.RemoteException;

public abstract interface l
  extends IInterface
{
  public abstract void a(Bundle paramBundle, int paramInt)
    throws RemoteException;
  
  public static abstract class a
    extends Binder
    implements l
  {
    public a()
    {
      attachInterface(this, "com.firebase.jobdispatcher.IJobCallback");
    }
    
    public IBinder asBinder()
    {
      return this;
    }
    
    public boolean onTransact(int paramInt1, Parcel paramParcel1, Parcel paramParcel2, int paramInt2)
      throws RemoteException
    {
      switch (paramInt1)
      {
      default: 
        return super.onTransact(paramInt1, paramParcel1, paramParcel2, paramInt2);
      case 1598968902: 
        paramParcel2.writeString("com.firebase.jobdispatcher.IJobCallback");
        return true;
      }
      paramParcel1.enforceInterface("com.firebase.jobdispatcher.IJobCallback");
      if (paramParcel1.readInt() != 0) {}
      for (paramParcel2 = (Bundle)Bundle.CREATOR.createFromParcel(paramParcel1);; paramParcel2 = null)
      {
        a(paramParcel2, paramParcel1.readInt());
        return true;
      }
    }
    
    private static final class a
      implements l
    {
      private IBinder Cw;
      
      a(IBinder paramIBinder)
      {
        this.Cw = paramIBinder;
      }
      
      /* Error */
      public final void a(Bundle paramBundle, int paramInt)
        throws RemoteException
      {
        // Byte code:
        //   0: invokestatic 28	android/os/Parcel:obtain	()Landroid/os/Parcel;
        //   3: astore_3
        //   4: aload_3
        //   5: ldc 30
        //   7: invokevirtual 34	android/os/Parcel:writeInterfaceToken	(Ljava/lang/String;)V
        //   10: aload_1
        //   11: ifnull +38 -> 49
        //   14: aload_3
        //   15: iconst_1
        //   16: invokevirtual 38	android/os/Parcel:writeInt	(I)V
        //   19: aload_1
        //   20: aload_3
        //   21: iconst_0
        //   22: invokevirtual 44	android/os/Bundle:writeToParcel	(Landroid/os/Parcel;I)V
        //   25: aload_3
        //   26: iload_2
        //   27: invokevirtual 38	android/os/Parcel:writeInt	(I)V
        //   30: aload_0
        //   31: getfield 18	com/firebase/jobdispatcher/l$a$a:Cw	Landroid/os/IBinder;
        //   34: iconst_1
        //   35: aload_3
        //   36: aconst_null
        //   37: iconst_1
        //   38: invokeinterface 50 5 0
        //   43: pop
        //   44: aload_3
        //   45: invokevirtual 53	android/os/Parcel:recycle	()V
        //   48: return
        //   49: aload_3
        //   50: iconst_0
        //   51: invokevirtual 38	android/os/Parcel:writeInt	(I)V
        //   54: goto -29 -> 25
        //   57: astore_1
        //   58: aload_3
        //   59: invokevirtual 53	android/os/Parcel:recycle	()V
        //   62: aload_1
        //   63: athrow
        // Local variable table:
        //   start	length	slot	name	signature
        //   0	64	0	this	a
        //   0	64	1	paramBundle	Bundle
        //   0	64	2	paramInt	int
        //   3	56	3	localParcel	Parcel
        // Exception table:
        //   from	to	target	type
        //   4	10	57	finally
        //   14	25	57	finally
        //   25	44	57	finally
        //   49	54	57	finally
      }
      
      public final IBinder asBinder()
      {
        return this.Cw;
      }
    }
  }
}


/* Location:              /home/qerwtr546/Documents/Vent Source/dex2jar-2.0/classes-dex2jar.jar!/com/firebase/jobdispatcher/l.class
 * Java compiler version: 6 (50.0)
 * JD-Core Version:       0.7.1
 */