package com.google.firebase.iid;

import android.app.PendingIntent;
import android.content.Context;
import android.content.Intent;
import android.os.Bundle;
import android.os.Looper;
import android.os.Messenger;
import android.util.Log;
import com.google.android.gms.c.f;
import java.io.IOException;

final class aa
{
  private static int bfD = 0;
  private static PendingIntent bfK;
  private final Context aUM;
  private final z beM;
  private final android.support.v4.g.m<String, f<Bundle>> bfL = new android.support.v4.g.m();
  private Messenger bfM;
  private Messenger bfN;
  private m bfO;
  
  public aa(Context paramContext, z paramz)
  {
    this.aUM = paramContext;
    this.beM = paramz;
    this.bfM = new Messenger(new ab(this, Looper.getMainLooper()));
  }
  
  private final void b(String paramString, Bundle paramBundle)
  {
    f localf;
    synchronized (this.bfL)
    {
      localf = (f)this.bfL.remove(paramString);
      if (localf == null)
      {
        paramString = String.valueOf(paramString);
        if (paramString.length() != 0)
        {
          paramString = "Missing callback for ".concat(paramString);
          Log.w("FirebaseInstanceId", paramString);
          return;
        }
        paramString = new String("Missing callback for ");
      }
    }
    localf.N(paramBundle);
  }
  
  private static void c(Context paramContext, Intent paramIntent)
  {
    try
    {
      if (bfK == null)
      {
        Intent localIntent = new Intent();
        localIntent.setPackage("com.google.example.invalidpackage");
        bfK = PendingIntent.getBroadcast(paramContext, 0, localIntent, 0);
      }
      paramIntent.putExtra("app", bfK);
      return;
    }
    finally {}
  }
  
  private final void e(Intent paramIntent)
  {
    String str1 = paramIntent.getStringExtra("error");
    if (str1 == null)
    {
      paramIntent = String.valueOf(paramIntent.getExtras());
      Log.w("FirebaseInstanceId", String.valueOf(paramIntent).length() + 49 + "Unexpected response, no error or registration id " + paramIntent);
      return;
    }
    if (Log.isLoggable("FirebaseInstanceId", 3))
    {
      localObject = String.valueOf(str1);
      if (((String)localObject).length() != 0)
      {
        localObject = "Received InstanceID error ".concat((String)localObject);
        Log.d("FirebaseInstanceId", (String)localObject);
      }
    }
    else
    {
      if (!str1.startsWith("|")) {
        break label229;
      }
      localObject = str1.split("\\|");
      if ((localObject.length > 2) && ("ID".equals(localObject[1]))) {
        break label182;
      }
      paramIntent = String.valueOf(str1);
      if (paramIntent.length() == 0) {
        break label169;
      }
    }
    label169:
    for (paramIntent = "Unexpected structured response ".concat(paramIntent);; paramIntent = new String("Unexpected structured response "))
    {
      Log.w("FirebaseInstanceId", paramIntent);
      return;
      localObject = new String("Received InstanceID error ");
      break;
    }
    label182:
    String str2 = localObject[2];
    str1 = localObject[3];
    Object localObject = str1;
    if (str1.startsWith(":")) {
      localObject = str1.substring(1);
    }
    b(str2, paramIntent.putExtra("error", (String)localObject).getExtras());
    return;
    label229:
    localObject = this.bfL;
    int i = 0;
    try
    {
      while (i < this.bfL.size())
      {
        b((String)this.bfL.keyAt(i), paramIntent.getExtras());
        i += 1;
      }
      return;
    }
    finally {}
  }
  
  private final Bundle n(Bundle paramBundle)
    throws IOException
  {
    Bundle localBundle2 = o(paramBundle);
    Bundle localBundle1 = localBundle2;
    if (localBundle2 != null)
    {
      localBundle1 = localBundle2;
      if (localBundle2.containsKey("google.messenger"))
      {
        paramBundle = o(paramBundle);
        localBundle1 = paramBundle;
        if (paramBundle != null)
        {
          localBundle1 = paramBundle;
          if (paramBundle.containsKey("google.messenger")) {
            localBundle1 = null;
          }
        }
      }
    }
    return localBundle1;
  }
  
  /* Error */
  private final Bundle o(Bundle arg1)
    throws IOException
  {
    // Byte code:
    //   0: invokestatic 289	com/google/firebase/iid/aa:uV	()Ljava/lang/String;
    //   3: astore_2
    //   4: new 190	com/google/android/gms/c/f
    //   7: dup
    //   8: invokespecial 290	com/google/android/gms/c/f:<init>	()V
    //   11: astore_3
    //   12: aload_0
    //   13: getfield 34	com/google/firebase/iid/aa:bfL	Landroid/support/v4/g/m;
    //   16: astore 4
    //   18: aload 4
    //   20: monitorenter
    //   21: aload_0
    //   22: getfield 34	com/google/firebase/iid/aa:bfL	Landroid/support/v4/g/m;
    //   25: aload_2
    //   26: aload_3
    //   27: invokevirtual 294	android/support/v4/g/m:put	(Ljava/lang/Object;Ljava/lang/Object;)Ljava/lang/Object;
    //   30: pop
    //   31: aload 4
    //   33: monitorexit
    //   34: aload_0
    //   35: getfield 38	com/google/firebase/iid/aa:beM	Lcom/google/firebase/iid/z;
    //   38: invokevirtual 299	com/google/firebase/iid/z:uQ	()I
    //   41: ifne +20 -> 61
    //   44: new 271	java/io/IOException
    //   47: dup
    //   48: ldc_w 301
    //   51: invokespecial 302	java/io/IOException:<init>	(Ljava/lang/String;)V
    //   54: athrow
    //   55: astore_1
    //   56: aload 4
    //   58: monitorexit
    //   59: aload_1
    //   60: athrow
    //   61: new 66	android/content/Intent
    //   64: dup
    //   65: invokespecial 201	android/content/Intent:<init>	()V
    //   68: astore 4
    //   70: aload 4
    //   72: ldc_w 304
    //   75: invokevirtual 207	android/content/Intent:setPackage	(Ljava/lang/String;)Landroid/content/Intent;
    //   78: pop
    //   79: aload_0
    //   80: getfield 38	com/google/firebase/iid/aa:beM	Lcom/google/firebase/iid/z;
    //   83: invokevirtual 299	com/google/firebase/iid/z:uQ	()I
    //   86: iconst_2
    //   87: if_icmpne +298 -> 385
    //   90: aload 4
    //   92: ldc_w 306
    //   95: invokevirtual 309	android/content/Intent:setAction	(Ljava/lang/String;)Landroid/content/Intent;
    //   98: pop
    //   99: aload 4
    //   101: aload_1
    //   102: invokevirtual 313	android/content/Intent:putExtras	(Landroid/os/Bundle;)Landroid/content/Intent;
    //   105: pop
    //   106: aload_0
    //   107: getfield 36	com/google/firebase/iid/aa:aUM	Landroid/content/Context;
    //   110: aload 4
    //   112: invokestatic 315	com/google/firebase/iid/aa:c	(Landroid/content/Context;Landroid/content/Intent;)V
    //   115: aload 4
    //   117: ldc_w 317
    //   120: new 223	java/lang/StringBuilder
    //   123: dup
    //   124: aload_2
    //   125: invokestatic 113	java/lang/String:valueOf	(Ljava/lang/Object;)Ljava/lang/String;
    //   128: invokevirtual 117	java/lang/String:length	()I
    //   131: iconst_5
    //   132: iadd
    //   133: invokespecial 226	java/lang/StringBuilder:<init>	(I)V
    //   136: ldc_w 319
    //   139: invokevirtual 232	java/lang/StringBuilder:append	(Ljava/lang/String;)Ljava/lang/StringBuilder;
    //   142: aload_2
    //   143: invokevirtual 232	java/lang/StringBuilder:append	(Ljava/lang/String;)Ljava/lang/StringBuilder;
    //   146: ldc -17
    //   148: invokevirtual 232	java/lang/StringBuilder:append	(Ljava/lang/String;)Ljava/lang/StringBuilder;
    //   151: invokevirtual 235	java/lang/StringBuilder:toString	()Ljava/lang/String;
    //   154: invokevirtual 260	android/content/Intent:putExtra	(Ljava/lang/String;Ljava/lang/String;)Landroid/content/Intent;
    //   157: pop
    //   158: ldc 103
    //   160: iconst_3
    //   161: invokestatic 109	android/util/Log:isLoggable	(Ljava/lang/String;I)Z
    //   164: ifeq +48 -> 212
    //   167: aload 4
    //   169: invokevirtual 169	android/content/Intent:getExtras	()Landroid/os/Bundle;
    //   172: invokestatic 113	java/lang/String:valueOf	(Ljava/lang/Object;)Ljava/lang/String;
    //   175: astore_1
    //   176: ldc 103
    //   178: new 223	java/lang/StringBuilder
    //   181: dup
    //   182: aload_1
    //   183: invokestatic 113	java/lang/String:valueOf	(Ljava/lang/Object;)Ljava/lang/String;
    //   186: invokevirtual 117	java/lang/String:length	()I
    //   189: bipush 8
    //   191: iadd
    //   192: invokespecial 226	java/lang/StringBuilder:<init>	(I)V
    //   195: ldc_w 321
    //   198: invokevirtual 232	java/lang/StringBuilder:append	(Ljava/lang/String;)Ljava/lang/StringBuilder;
    //   201: aload_1
    //   202: invokevirtual 232	java/lang/StringBuilder:append	(Ljava/lang/String;)Ljava/lang/StringBuilder;
    //   205: invokevirtual 235	java/lang/StringBuilder:toString	()Ljava/lang/String;
    //   208: invokestatic 127	android/util/Log:d	(Ljava/lang/String;Ljava/lang/String;)I
    //   211: pop
    //   212: aload 4
    //   214: ldc 75
    //   216: aload_0
    //   217: getfield 56	com/google/firebase/iid/aa:bfM	Landroid/os/Messenger;
    //   220: invokevirtual 219	android/content/Intent:putExtra	(Ljava/lang/String;Landroid/os/Parcelable;)Landroid/content/Intent;
    //   223: pop
    //   224: aload_0
    //   225: getfield 89	com/google/firebase/iid/aa:bfN	Landroid/os/Messenger;
    //   228: ifnonnull +10 -> 238
    //   231: aload_0
    //   232: getfield 87	com/google/firebase/iid/aa:bfO	Lcom/google/firebase/iid/m;
    //   235: ifnull +192 -> 427
    //   238: invokestatic 325	android/os/Message:obtain	()Landroid/os/Message;
    //   241: astore_1
    //   242: aload_1
    //   243: aload 4
    //   245: putfield 64	android/os/Message:obj	Ljava/lang/Object;
    //   248: aload_0
    //   249: getfield 89	com/google/firebase/iid/aa:bfN	Landroid/os/Messenger;
    //   252: ifnull +145 -> 397
    //   255: aload_0
    //   256: getfield 89	com/google/firebase/iid/aa:bfN	Landroid/os/Messenger;
    //   259: aload_1
    //   260: invokevirtual 329	android/os/Messenger:send	(Landroid/os/Message;)V
    //   263: aload_3
    //   264: getfield 333	com/google/android/gms/c/f:bdU	Lcom/google/android/gms/c/r;
    //   267: astore_1
    //   268: getstatic 339	java/util/concurrent/TimeUnit:MILLISECONDS	Ljava/util/concurrent/TimeUnit;
    //   271: astore_3
    //   272: ldc_w 341
    //   275: invokestatic 346	com/google/android/gms/common/internal/ae:bh	(Ljava/lang/String;)V
    //   278: aload_1
    //   279: ldc_w 348
    //   282: invokestatic 351	com/google/android/gms/common/internal/ae:g	(Ljava/lang/Object;Ljava/lang/Object;)Ljava/lang/Object;
    //   285: pop
    //   286: aload_3
    //   287: ldc_w 353
    //   290: invokestatic 351	com/google/android/gms/common/internal/ae:g	(Ljava/lang/Object;Ljava/lang/Object;)Ljava/lang/Object;
    //   293: pop
    //   294: aload_1
    //   295: invokevirtual 358	com/google/android/gms/c/e:isComplete	()Z
    //   298: ifne +165 -> 463
    //   301: new 360	com/google/android/gms/c/h$a
    //   304: dup
    //   305: iconst_0
    //   306: invokespecial 363	com/google/android/gms/c/h$a:<init>	(B)V
    //   309: astore 4
    //   311: aload_1
    //   312: aload 4
    //   314: invokestatic 368	com/google/android/gms/c/h:a	(Lcom/google/android/gms/c/e;Lcom/google/android/gms/c/h$b;)V
    //   317: aload 4
    //   319: getfield 372	com/google/android/gms/c/h$a:aDl	Ljava/util/concurrent/CountDownLatch;
    //   322: ldc2_w 373
    //   325: aload_3
    //   326: invokevirtual 380	java/util/concurrent/CountDownLatch:await	(JLjava/util/concurrent/TimeUnit;)Z
    //   329: ifne +134 -> 463
    //   332: new 284	java/util/concurrent/TimeoutException
    //   335: dup
    //   336: ldc_w 382
    //   339: invokespecial 383	java/util/concurrent/TimeoutException:<init>	(Ljava/lang/String;)V
    //   342: athrow
    //   343: astore_1
    //   344: ldc 103
    //   346: ldc_w 385
    //   349: invokestatic 184	android/util/Log:w	(Ljava/lang/String;Ljava/lang/String;)I
    //   352: pop
    //   353: new 271	java/io/IOException
    //   356: dup
    //   357: ldc_w 387
    //   360: invokespecial 302	java/io/IOException:<init>	(Ljava/lang/String;)V
    //   363: athrow
    //   364: astore_3
    //   365: aload_0
    //   366: getfield 34	com/google/firebase/iid/aa:bfL	Landroid/support/v4/g/m;
    //   369: astore_1
    //   370: aload_1
    //   371: monitorenter
    //   372: aload_0
    //   373: getfield 34	com/google/firebase/iid/aa:bfL	Landroid/support/v4/g/m;
    //   376: aload_2
    //   377: invokevirtual 188	android/support/v4/g/m:remove	(Ljava/lang/Object;)Ljava/lang/Object;
    //   380: pop
    //   381: aload_1
    //   382: monitorexit
    //   383: aload_3
    //   384: athrow
    //   385: aload 4
    //   387: ldc_w 389
    //   390: invokevirtual 309	android/content/Intent:setAction	(Ljava/lang/String;)Landroid/content/Intent;
    //   393: pop
    //   394: goto -295 -> 99
    //   397: aload_0
    //   398: getfield 87	com/google/firebase/iid/aa:bfO	Lcom/google/firebase/iid/m;
    //   401: aload_1
    //   402: invokevirtual 390	com/google/firebase/iid/m:send	(Landroid/os/Message;)V
    //   405: goto -142 -> 263
    //   408: astore_1
    //   409: ldc 103
    //   411: iconst_3
    //   412: invokestatic 109	android/util/Log:isLoggable	(Ljava/lang/String;I)Z
    //   415: ifeq +12 -> 427
    //   418: ldc 103
    //   420: ldc_w 392
    //   423: invokestatic 127	android/util/Log:d	(Ljava/lang/String;Ljava/lang/String;)I
    //   426: pop
    //   427: aload_0
    //   428: getfield 38	com/google/firebase/iid/aa:beM	Lcom/google/firebase/iid/z;
    //   431: invokevirtual 299	com/google/firebase/iid/z:uQ	()I
    //   434: iconst_2
    //   435: if_icmpne +15 -> 450
    //   438: aload_0
    //   439: getfield 36	com/google/firebase/iid/aa:aUM	Landroid/content/Context;
    //   442: aload 4
    //   444: invokevirtual 397	android/content/Context:sendBroadcast	(Landroid/content/Intent;)V
    //   447: goto -184 -> 263
    //   450: aload_0
    //   451: getfield 36	com/google/firebase/iid/aa:aUM	Landroid/content/Context;
    //   454: aload 4
    //   456: invokevirtual 401	android/content/Context:startService	(Landroid/content/Intent;)Landroid/content/ComponentName;
    //   459: pop
    //   460: goto -197 -> 263
    //   463: aload_1
    //   464: invokestatic 404	com/google/android/gms/c/h:b	(Lcom/google/android/gms/c/e;)Ljava/lang/Object;
    //   467: checkcast 171	android/os/Bundle
    //   470: astore_3
    //   471: aload_0
    //   472: getfield 34	com/google/firebase/iid/aa:bfL	Landroid/support/v4/g/m;
    //   475: astore_1
    //   476: aload_1
    //   477: monitorenter
    //   478: aload_0
    //   479: getfield 34	com/google/firebase/iid/aa:bfL	Landroid/support/v4/g/m;
    //   482: aload_2
    //   483: invokevirtual 188	android/support/v4/g/m:remove	(Ljava/lang/Object;)Ljava/lang/Object;
    //   486: pop
    //   487: aload_1
    //   488: monitorexit
    //   489: aload_3
    //   490: areturn
    //   491: astore_2
    //   492: aload_1
    //   493: monitorexit
    //   494: aload_2
    //   495: athrow
    //   496: astore_1
    //   497: new 271	java/io/IOException
    //   500: dup
    //   501: aload_1
    //   502: invokespecial 407	java/io/IOException:<init>	(Ljava/lang/Throwable;)V
    //   505: athrow
    //   506: astore_2
    //   507: aload_1
    //   508: monitorexit
    //   509: aload_2
    //   510: athrow
    //   511: astore_1
    //   512: goto -168 -> 344
    // Local variable table:
    //   start	length	slot	name	signature
    //   0	515	0	this	aa
    //   3	480	2	str	String
    //   491	4	2	localObject1	Object
    //   506	4	2	localObject2	Object
    //   11	315	3	localObject3	Object
    //   364	20	3	localObject4	Object
    //   470	20	3	localBundle	Bundle
    //   16	439	4	localObject5	Object
    // Exception table:
    //   from	to	target	type
    //   21	34	55	finally
    //   56	59	55	finally
    //   263	343	343	java/lang/InterruptedException
    //   463	471	343	java/lang/InterruptedException
    //   263	343	364	finally
    //   344	364	364	finally
    //   463	471	364	finally
    //   497	506	364	finally
    //   248	263	408	android/os/RemoteException
    //   397	405	408	android/os/RemoteException
    //   478	489	491	finally
    //   492	494	491	finally
    //   263	343	496	java/util/concurrent/ExecutionException
    //   463	471	496	java/util/concurrent/ExecutionException
    //   372	383	506	finally
    //   507	509	506	finally
    //   263	343	511	java/util/concurrent/TimeoutException
    //   463	471	511	java/util/concurrent/TimeoutException
  }
  
  private static String uV()
  {
    try
    {
      int i = bfD;
      bfD = i + 1;
      String str = Integer.toString(i);
      return str;
    }
    finally
    {
      localObject = finally;
      throw ((Throwable)localObject);
    }
  }
  
  /* Error */
  final Bundle m(Bundle paramBundle)
    throws IOException
  {
    // Byte code:
    //   0: aload_0
    //   1: getfield 38	com/google/firebase/iid/aa:beM	Lcom/google/firebase/iid/z;
    //   4: invokevirtual 415	com/google/firebase/iid/z:uT	()I
    //   7: ldc_w 416
    //   10: if_icmplt +171 -> 181
    //   13: aload_0
    //   14: getfield 36	com/google/firebase/iid/aa:aUM	Landroid/content/Context;
    //   17: invokestatic 422	com/google/firebase/iid/o:ao	(Landroid/content/Context;)Lcom/google/firebase/iid/o;
    //   20: astore_2
    //   21: aload_2
    //   22: new 424	com/google/firebase/iid/y
    //   25: dup
    //   26: aload_2
    //   27: invokevirtual 427	com/google/firebase/iid/o:uL	()I
    //   30: aload_1
    //   31: invokespecial 430	com/google/firebase/iid/y:<init>	(ILandroid/os/Bundle;)V
    //   34: invokevirtual 433	com/google/firebase/iid/o:a	(Lcom/google/firebase/iid/w;)Lcom/google/android/gms/c/e;
    //   37: astore_2
    //   38: ldc_w 341
    //   41: invokestatic 346	com/google/android/gms/common/internal/ae:bh	(Ljava/lang/String;)V
    //   44: aload_2
    //   45: ldc_w 348
    //   48: invokestatic 351	com/google/android/gms/common/internal/ae:g	(Ljava/lang/Object;Ljava/lang/Object;)Ljava/lang/Object;
    //   51: pop
    //   52: aload_2
    //   53: invokevirtual 358	com/google/android/gms/c/e:isComplete	()Z
    //   56: ifeq +13 -> 69
    //   59: aload_2
    //   60: invokestatic 404	com/google/android/gms/c/h:b	(Lcom/google/android/gms/c/e;)Ljava/lang/Object;
    //   63: astore_2
    //   64: aload_2
    //   65: checkcast 171	android/os/Bundle
    //   68: areturn
    //   69: new 360	com/google/android/gms/c/h$a
    //   72: dup
    //   73: iconst_0
    //   74: invokespecial 363	com/google/android/gms/c/h$a:<init>	(B)V
    //   77: astore_3
    //   78: aload_2
    //   79: aload_3
    //   80: invokestatic 368	com/google/android/gms/c/h:a	(Lcom/google/android/gms/c/e;Lcom/google/android/gms/c/h$b;)V
    //   83: aload_3
    //   84: getfield 372	com/google/android/gms/c/h$a:aDl	Ljava/util/concurrent/CountDownLatch;
    //   87: invokevirtual 435	java/util/concurrent/CountDownLatch:await	()V
    //   90: aload_2
    //   91: invokestatic 404	com/google/android/gms/c/h:b	(Lcom/google/android/gms/c/e;)Ljava/lang/Object;
    //   94: astore_2
    //   95: goto -31 -> 64
    //   98: astore_2
    //   99: ldc 103
    //   101: iconst_3
    //   102: invokestatic 109	android/util/Log:isLoggable	(Ljava/lang/String;I)Z
    //   105: ifeq +44 -> 149
    //   108: aload_2
    //   109: invokestatic 113	java/lang/String:valueOf	(Ljava/lang/Object;)Ljava/lang/String;
    //   112: astore_3
    //   113: ldc 103
    //   115: new 223	java/lang/StringBuilder
    //   118: dup
    //   119: aload_3
    //   120: invokestatic 113	java/lang/String:valueOf	(Ljava/lang/Object;)Ljava/lang/String;
    //   123: invokevirtual 117	java/lang/String:length	()I
    //   126: bipush 22
    //   128: iadd
    //   129: invokespecial 226	java/lang/StringBuilder:<init>	(I)V
    //   132: ldc_w 437
    //   135: invokevirtual 232	java/lang/StringBuilder:append	(Ljava/lang/String;)Ljava/lang/StringBuilder;
    //   138: aload_3
    //   139: invokevirtual 232	java/lang/StringBuilder:append	(Ljava/lang/String;)Ljava/lang/StringBuilder;
    //   142: invokevirtual 235	java/lang/StringBuilder:toString	()Ljava/lang/String;
    //   145: invokestatic 127	android/util/Log:d	(Ljava/lang/String;Ljava/lang/String;)I
    //   148: pop
    //   149: aload_2
    //   150: invokevirtual 443	java/lang/Exception:getCause	()Ljava/lang/Throwable;
    //   153: instanceof 445
    //   156: ifeq +23 -> 179
    //   159: aload_2
    //   160: invokevirtual 443	java/lang/Exception:getCause	()Ljava/lang/Throwable;
    //   163: checkcast 445	com/google/firebase/iid/x
    //   166: getfield 448	com/google/firebase/iid/x:aCs	I
    //   169: iconst_4
    //   170: if_icmpne +9 -> 179
    //   173: aload_0
    //   174: aload_1
    //   175: invokespecial 450	com/google/firebase/iid/aa:n	(Landroid/os/Bundle;)Landroid/os/Bundle;
    //   178: areturn
    //   179: aconst_null
    //   180: areturn
    //   181: aload_0
    //   182: aload_1
    //   183: invokespecial 450	com/google/firebase/iid/aa:n	(Landroid/os/Bundle;)Landroid/os/Bundle;
    //   186: areturn
    //   187: astore_2
    //   188: goto -89 -> 99
    // Local variable table:
    //   start	length	slot	name	signature
    //   0	191	0	this	aa
    //   0	191	1	paramBundle	Bundle
    //   20	75	2	localObject1	Object
    //   98	62	2	localInterruptedException	InterruptedException
    //   187	1	2	localExecutionException	java.util.concurrent.ExecutionException
    //   77	62	3	localObject2	Object
    // Exception table:
    //   from	to	target	type
    //   38	64	98	java/lang/InterruptedException
    //   64	69	98	java/lang/InterruptedException
    //   69	95	98	java/lang/InterruptedException
    //   38	64	187	java/util/concurrent/ExecutionException
    //   64	69	187	java/util/concurrent/ExecutionException
    //   69	95	187	java/util/concurrent/ExecutionException
  }
}


/* Location:              /home/qerwtr546/Documents/Vent Source/dex2jar-2.0/classes-dex2jar.jar!/com/google/firebase/iid/aa.class
 * Java compiler version: 6 (50.0)
 * JD-Core Version:       0.7.1
 */